engr_colab_github/__init__.py
engr_colab_github/git_operations.py
engr_colab_github/repo_manager.py
engr_colab_github/setup.py
engr_colab_github/utils.py
engr_colab_github-1.0.dist-info/LICENSE
engr_colab_github-1.0.dist-info/METADATA
engr_colab_github-1.0.dist-info/WHEEL
engr_colab_github-1.0.dist-info/entry_points.txt
engr_colab_github-1.0.dist-info/top_level.txt
engr_colab_github-1.0.dist-info/RECORD
